libpHash.so
pHash.h
pHashPy-0.1.2.dist-info/RECORD
pHashPy-0.1.2.dist-info/top_level.txt
pHashPy-0.1.2.dist-info/METADATA
pHashPy-0.1.2.dist-info/WHEEL
pHashPy-0.1.2.dist-info/entry_points.txt
pHashPy/__init__.py
pHashPy/helpers.py
pHashPy/image.py
pHashPy/__main__.py
pHashPy/video.py
.libslibpHash/libfdk-aac-3435a0d9.so.1.0.0
.libslibpHash/libschroedinger-1-a9b52fb4.0.so.0.11.0
.libslibpHash/libtheoradec-c1ea91f0.so.1.1.4
.libslibpHash/libnettle-e96a3a60.so.4.7
.libslibpHash/libxvidcore-1bf58c41.so.4.3
.libslibpHash/libopus-abf1ee53.so.0.3.0
.libslibpHash/libsamplerate-6fb223e4.so.0.1.8
.libslibpHash/libgomp-7c85b1e2.so.1.0.0
.libslibpHash/libvorbisenc-e32e3ab5.so.2.0.9
.libslibpHash/libp11-kit-f8c4ccf1.so.0.3.0
.libslibpHash/libz-d8a329de.so.1.2.7
.libslibpHash/libjbig-78348776.so.2.0
.libslibpHash/libbz2-a273e504.so.1.0.6
.libslibpHash/libsoxr-6993ef22.so.0.1.1
.libslibpHash/libnuma-9e22c8b3.so.1.0.0
.libslibpHash/libavcodec-3aae44c8.so.56.60.100
.libslibpHash/liborc-0-14d3dc57.4.so.0.25.0
.libslibpHash/libogg-24eaa32b.so.0.8.0
.libslibpHash/libavformat-7cef39b7.so.56.40.101
.libslibpHash/libffi-cdb47bd8.so.6.0.1
.libslibpHash/libva-cc18982b.so.1.4000.0
.libslibpHash/libgnutls-e57e6213.so.28.43.3
.libslibpHash/libvo-amrwbenc-c49133f2.so.0.0.3
.libslibpHash/libx264-3ebd7920.so.142
.libslibpHash/libvorbis-02341991.so.0.4.6
.libslibpHash/libhogweed-b4b90609.so.2.5
.libslibpHash/libgmp-afec2dd4.so.10.2.0
.libslibpHash/libjpeg-43436dd5.so.62.1.0
.libslibpHash/libFLAC-b0904aee.so.8.3.0
.libslibpHash/libtheoraenc-b005fd1d.so.1.1.2
.libslibpHash/libopencore-amrwb-bb594124.so.0.0.3
.libslibpHash/libsndfile-2ee11aa9.so.1.0.25
.libslibpHash/libmp3lame-222ac6d8.so.0.0.0
.libslibpHash/libswscale-51e3e7e9.so.3.1.101
.libslibpHash/libpng15-c2ffaf3d.so.15.13.0
.libslibpHash/libopenjpeg-7c5c81a9.so.1.5.1
.libslibpHash/libopencore-amrnb-e8aeca90.so.0.0.3
.libslibpHash/libtiff-f425fce6.so.5.2.0
.libslibpHash/libswresample-6bcf0fb4.so.1.2.101
.libslibpHash/libgsm-ed01cacd.so.1.0.12
.libslibpHash/libspeex-56b87c1d.so.1.5.0
.libslibpHash/libavutil-2b8b59eb.so.54.31.100
