Metadata-Version: 2.1
Name: pHashPy
Version: 0.1.2
Summary: Python bindings for the pHash (perceptual hashing) library.
Home-page: https://github.com/dries007/pHashPy
Author: Dries007
Author-email: admin@dries007.net
License: gpl-3
Platform: UNKNOWN
Classifier: Programming Language :: Python :: 3 :: Only
Classifier: License :: OSI Approved :: GNU Lesser General Public License v3 or later (LGPLv3+)
Classifier: Operating System :: POSIX :: Linux
Requires-Python: >=3.6
